rest_framework_admin/__init__.py
rest_framework_admin/urls.py
rest_framework_admin/auth/__init__.py
rest_framework_admin/auth/apps.py
rest_framework_admin/auth/models.py
rest_framework_admin/auth/serializers.py
rest_framework_admin/auth/settings.py
rest_framework_admin/auth/tests.py
rest_framework_admin/auth/urls.py
rest_framework_admin/auth/views.py
rest_framework_admin/auth/jwt/__init__.py
rest_framework_admin/auth/jwt/backends.py
rest_framework_admin/auth/jwt/exceptions.py
rest_framework_admin/auth/jwt/middlewares.py
rest_framework_admin/auth/jwt/serializers.py
rest_framework_admin/auth/jwt/urls.py
rest_framework_admin/auth/jwt/views.py
rest_framework_admin/auth/jwt/utils/__init__.py
rest_framework_admin/auth/jwt/utils/blacklist.py
rest_framework_admin/auth/model/__init__.py
rest_framework_admin/auth/model/backends.py
rest_framework_admin/doc/__init__.py
rest_framework_admin/doc/admin.py
rest_framework_admin/doc/apps.py
rest_framework_admin/doc/models.py
rest_framework_admin/doc/urls.py
rest_framework_admin/doc/migrations/__init__.py
rest_framework_admin/group/__init__.py
rest_framework_admin/group/filters.py
rest_framework_admin/group/models.py
rest_framework_admin/group/serializers.py
rest_framework_admin/role/__init__.py
rest_framework_admin/role/admin.py
rest_framework_admin/role/apps.py
rest_framework_admin/role/configs.py
rest_framework_admin/role/filters.py
rest_framework_admin/role/models.py
rest_framework_admin/role/permissions.py
rest_framework_admin/role/serializers.py
rest_framework_admin/role/services.py
rest_framework_admin/role/settings.py
rest_framework_admin/role/urls.py
rest_framework_admin/role/views.py
rest_framework_admin/role/migrations/0001_initial.py
rest_framework_admin/role/migrations/__init__.py
rest_framework_admin/role/permission/__init__.py
rest_framework_admin/role/permission/filters.py
rest_framework_admin/role/permission/models.py
rest_framework_admin/role/permission/permissions.py
djangorestframework_admin-0.0.8.dist-info/LICENSE
djangorestframework_admin-0.0.8.dist-info/METADATA
djangorestframework_admin-0.0.8.dist-info/WHEEL
djangorestframework_admin-0.0.8.dist-info/top_level.txt
djangorestframework_admin-0.0.8.dist-info/RECORD
