Metadata-Version: 2.1
Name: djangorestframework-admin
Version: 0.0.8
Summary: Admin Backend Web APIs for DjangoRestFramework, made easy.
Home-page: https://gitee.com/iamfengdy/djangorestframework-admin
Author: fengdy
Author-email: iamfengdy@126.com
License: BSD
Project-URL: Source, https://gitee.com/iamfengdy/djangorestframework-admin
Keywords: djangorestframework admin
Platform: UNKNOWN
Classifier: Development Status :: 4 - Beta
Classifier: Environment :: Web Environment
Classifier: Framework :: Django :: 4.1
Classifier: Intended Audience :: Developers
Classifier: License :: OSI Approved :: BSD License
Classifier: Operating System :: OS Independent
Classifier: Programming Language :: Python
Classifier: Programming Language :: Python :: 3.10
Classifier: Programming Language :: Python :: 3 :: Only
Classifier: Topic :: Internet :: WWW/HTTP
Requires-Python: >=3.10
License-File: LICENSE
Requires-Dist: djangorestframework-util
Requires-Dist: django-filter (==23.1)
Requires-Dist: djangorestframework-simplejwt (==5.3.0)
Requires-Dist: pycryptodome (==3.19.0)
Requires-Dist: django-cors-headers (==4.3.1)
